mcp_server_cvm/__init__.py
mcp_server_cvm/client.py
mcp_server_cvm/run_instances.py
mcp_server_cvm/server.py
mcp_server_cvm/tool_cvm.py
mcp_server_cvm/tool_monitor.py
mcp_server_cvm/tool_vpc.py
mcp_server_cvm-0.1.12.dist-info/METADATA
mcp_server_cvm-0.1.12.dist-info/WHEEL
mcp_server_cvm-0.1.12.dist-info/entry_points.txt
mcp_server_cvm-0.1.12.dist-info/RECORD
