Metadata-Version: 2.4
Name: mcp-server-cvm
Version: 0.1.12
Summary: MCP Server for Tencent Cloud CVM
Requires-Python: >=3.10
Requires-Dist: mcp>=1.0.0
Requires-Dist: tencentcloud-sdk-python-common==3.0.1356
Requires-Dist: tencentcloud-sdk-python-cvm==3.0.1356
Requires-Dist: tencentcloud-sdk-python-monitor==3.0.1356
Requires-Dist: tencentcloud-sdk-python-vpc==3.0.1356
